signalgrid/__init__.py
signalgrid/client.py
signalgrid-1.0.0.dist-info/METADATA
signalgrid-1.0.0.dist-info/WHEEL
signalgrid-1.0.0.dist-info/top_level.txt
signalgrid-1.0.0.dist-info/RECORD
