Metadata-Version: 2.4
Name: signalgrid
Version: 1.0.0
Summary: Official Python client for Signalgrid push-notification API
Author-email: Signalgrid <support@signalgrid.co>
License: MIT
Requires-Python: >=3.9
